[
    {
        "points": [
            [
                1407,
                746
            ],
            [
                1319,
                764
            ],
            [
                1227,
                682
            ],
            [
                1301,
                664
            ]
        ]
    },
    {
        "points": [
            [
                1325,
                771
            ],
            [
                1240,
                787
            ],
            [
                1137,
                683
            ],
            [
                1231,
                683
            ]
        ]
    },
    {
        "points": [
            [
                1234,
                789
            ],
            [
                1134,
                819
            ],
            [
                1047,
                705
            ],
            [
                1137,
                687
            ]
        ]
    },
    {
        "points": [
            [
                1120,
                810
            ],
            [
                1010,
                834
            ],
            [
                949,
                711
            ],
            [
                1029,
                695
            ]
        ]
    },
    {
        "points": [
            [
                1026,
                832
            ],
            [
                908,
                849
            ],
            [
                832,
                716
            ],
            [
                935,
                708
            ]
        ]
    },
    {
        "points": [
            [
                904,
                849
            ],
            [
                775,
                867
            ],
            [
                727,
                729
            ],
            [
                836,
                714
            ]
        ]
    },
    {
        "points": [
            [
                780,
                862
            ],
            [
                650,
                879
            ],
            [
                614,
                746
            ],
            [
                724,
                731
            ]
        ]
    },
    {
        "points": [
            [
                650,
                876
            ],
            [
                521,
                893
            ],
            [
                500,
                758
            ],
            [
                621,
                749
            ]
        ]
    },
    {
        "points": [
            [
                511,
                893
            ],
            [
                390,
                904
            ],
            [
                390,
                768
            ],
            [
                494,
                756
            ]
        ]
    },
    {
        "points": [
            [
                382,
                902
            ],
            [
                257,
                914
            ],
            [
                280,
                773
            ],
            [
                391,
                773
            ]
        ]
    },
    {
        "points": [
            [
                255,
                908
            ],
            [
                144,
                911
            ],
            [
                180,
                774
            ],
            [
                272,
                770
            ]
        ]
    },
    {
        "points": [
            [
                136,
                913
            ],
            [
                31,
                916
            ],
            [
                83,
                779
            ],
            [
                177,
                776
            ]
        ]
    },
    {
        "points": [
            [
                5,
                919
            ],
            [
                28,
                914
            ],
            [
                82,
                779
            ],
            [
                8,
                779
            ]
        ]
    },
    {
        "points": [
            [
                1624,
                696
            ],
            [
                1679,
                686
            ],
            [
                1590,
                620
            ],
            [
                1540,
                626
            ]
        ]
    },
    {
        "points": [
            [
                1666,
                686
            ],
            [
                1727,
                667
            ],
            [
                1632,
                611
            ],
            [
                1593,
                620
            ]
        ]
    },
    {
        "points": [
            [
                1727,
                670
            ],
            [
                1766,
                656
            ],
            [
                1682,
                610
            ],
            [
                1629,
                610
            ]
        ]
    },
    {
        "points": [
            [
                1771,
                665
            ],
            [
                1802,
                647
            ],
            [
                1723,
                604
            ],
            [
                1679,
                613
            ]
        ]
    },
    {
        "points": [
            [
                1805,
                649
            ],
            [
                1838,
                637
            ],
            [
                1751,
                583
            ],
            [
                1709,
                593
            ]
        ]
    }
]